am_i_connected/__init__.py
am_i_connected/am_i_connected.py
am_i_connected-0.1.4.dist-info/LICENSE
am_i_connected-0.1.4.dist-info/METADATA
am_i_connected-0.1.4.dist-info/WHEEL
am_i_connected-0.1.4.dist-info/top_level.txt
am_i_connected-0.1.4.dist-info/RECORD
