Metadata-Version: 2.1
Name: am-i-connected
Version: 0.1.4
Summary: The simplest way to check if internet access is available.
Home-page: https://github.com/yanncabral/am_i_connected
Author: Yann Cabral
Author-email: iamyanndias@gmail.com
License: MIT
Download-URL: https://pypi.org/project/am_i_connected/
Keywords: internet,check,connection
Platform: UNKNOWN
